<?xml version="1.0" encoding="UTF-8"?>
<files psalm-version="5.9.0@8b9ad1eb9e8b7d3101f949291da2b9f7767cd163">
  <file src="src/Action/ConvertPaymentAction.php">
    <DeprecatedInterface>
      <code><![CDATA[$this->payum->getTokenFactory()]]></code>
    </DeprecatedInterface>
    <InvalidArrayOffset>
      <code><![CDATA[$splittedStreet['houseNumberParts']['base']]]></code>
      <code><![CDATA[$splittedStreet['houseNumberParts']['extension']]]></code>
    </InvalidArrayOffset>
    <MixedAssignment>
      <code><![CDATA[$details['house_extension']]]></code>
      <code><![CDATA[$details['house_number']]]></code>
    </MixedAssignment>
    <MoreSpecificImplementedParamType>
      <code>$request</code>
    </MoreSpecificImplementedParamType>
    <PropertyNotSetInConstructor>
      <code>ConvertPaymentAction</code>
      <code>ConvertPaymentAction</code>
    </PropertyNotSetInConstructor>
    <RedundantConditionGivenDocblockType>
      <code>notNull</code>
    </RedundantConditionGivenDocblockType>
  </file>
  <file src="src/Action/NotifyAction.php">
    <MixedArrayAccess>
      <code><![CDATA[$httpRequest->headers['quickpay-checksum-sha256']]]></code>
      <code><![CDATA[$httpRequest->headers['quickpay-checksum-sha256'][0]]]></code>
    </MixedArrayAccess>
    <MoreSpecificImplementedParamType>
      <code>$request</code>
    </MoreSpecificImplementedParamType>
  </file>
  <file src="src/Action/StatusAction.php">
    <MoreSpecificImplementedParamType>
      <code>$request</code>
    </MoreSpecificImplementedParamType>
  </file>
  <file src="src/Checker/StreetEligibilityChecker.php">
    <MixedArrayAccess>
      <code><![CDATA[$splittedStreet['houseNumberParts']['base']]]></code>
      <code><![CDATA[$splittedStreet['houseNumberParts']['extension']]]></code>
    </MixedArrayAccess>
  </file>
</files>
